[{"statusCode":3,"price":1250.0,"orderNo":"JQ0001","commodityInfo":{"id":3,"name":"234","subheading":null,"brandId":null,"brandBasics":{"id":3,"brandNameZh":null,"brandNameEn":null,"brandAbbreviation":null,"logo":null,"nation":null,"affiliationGroup":null,"deviceType":null,"maintainStatus":null,"createDate":null,"updateDate":"","flag":null},"commodityLabel":null,"erpNo":null,"productNo":null,"specification":"zxc","origin":null,"modelNumber":null,"deviceFit":null,"deviceId":null,"deviceInfo":{"id":3,"deviceName":null,"deviceTypeId":null,"deviceTypeBasics":{"id":3,"deviceCode":null,"deviceType":null,"createDate":null,"updateDate":null,"flag":null},"deviceModelNum":null,"deviceBrandId":null,"brandBasics":null,"createDate":null,"updateDate":null,"flag":null},"marketPrice":null,"costPrice":null,"vipPrice":54.0,"salesPrice":5234.0,"salesStartTime":"","salesEndTime":"","pinkageFlag":null,"freight":null,"inventoryNumber":null,"salesVolume":null,"putawayLocation":null,"putawayFlag":null,"putawayTime":"","coverImage":"http://192.168.10.26:9999/group1/M00/00/0C/wKgKGlnxPyyAD2BCAAJevUGze20363.jpg","profileImage":null,"commodityDetailImage":null,"createDate":"","updateDate":"","recommendFlag":null,"flag":null,"freightDetail":null},"freight":20.0,"mallMemberId":2,"number":2,"statusNameCustomer":"待发货","createDate":"2017-11-01 14:19:52"}]